ixia/__init__.py
ixia/__main__.py
ixia/date_time.py
ixia/distributions.py
ixia/integers.py
ixia/py.typed
ixia/sequences.py
ixia/strings.py
ixia-2.0.0.dist-info/METADATA
ixia-2.0.0.dist-info/WHEEL
ixia-2.0.0.dist-info/licenses/LICENSE
ixia-2.0.0.dist-info/RECORD
