Metadata-Version: 2.4
Name: ixia
Version: 2.0.0
Summary: Connecting secrets' security with random's versatility
Project-URL: documentation, https://trag1c.github.io/ixia/
Project-URL: repository, https://github.com/trag1c/ixia
Author-email: trag1c <trag1cdev@yahoo.com>
License: Copyright (c) 2022–2025 trag1c
License-File: LICENSE
Requires-Python: >=3.9
